LICENSE
MANIFEST.in
README.md
setup.py
Flask_MDEditor.egg-info/PKG-INFO
Flask_MDEditor.egg-info/SOURCES.txt
Flask_MDEditor.egg-info/dependency_links.txt
Flask_MDEditor.egg-info/requires.txt
Flask_MDEditor.egg-info/top_level.txt
flask_mdeditor/__init__.py
flask_mdeditor/fields.py
flask_mdeditor/utils.py
flask_mdeditor/static/mdeditor/css/editormd.css
flask_mdeditor/static/mdeditor/css/editormd.logo.css
flask_mdeditor/static/mdeditor/css/editormd.logo.min.css
flask_mdeditor/static/mdeditor/css/editormd.min.css
flask_mdeditor/static/mdeditor/css/editormd.preview.css
flask_mdeditor/static/mdeditor/css/editormd.preview.min.css
flask_mdeditor/static/mdeditor/css/style.css
flask_mdeditor/static/mdeditor/fonts/FontAwesome.otf
flask_mdeditor/static/mdeditor/fonts/editormd-logo.eot
flask_mdeditor/static/mdeditor/fonts/editormd-logo.svg
flask_mdeditor/static/mdeditor/fonts/editormd-logo.ttf
flask_mdeditor/static/mdeditor/fonts/editormd-logo.woff
flask_mdeditor/static/mdeditor/fonts/fontawesome-webfont.eot
flask_mdeditor/static/mdeditor/fonts/fontawesome-webfont.svg
flask_mdeditor/static/mdeditor/fonts/fontawesome-webfont.ttf
flask_mdeditor/static/mdeditor/fonts/fontawesome-webfont.woff
flask_mdeditor/static/mdeditor/fonts/fontawesome-webfont.woff2
flask_mdeditor/static/mdeditor/images/loading.gif
flask_mdeditor/static/mdeditor/images/loading@2x.gif
flask_mdeditor/static/mdeditor/images/loading@3x.gif
flask_mdeditor/static/mdeditor/images/logos/editormd-favicon-16x16.ico
flask_mdeditor/static/mdeditor/images/logos/editormd-favicon-24x24.ico
flask_mdeditor/static/mdeditor/images/logos/editormd-favicon-32x32.ico
flask_mdeditor/static/mdeditor/images/logos/editormd-favicon-48x48.ico
flask_mdeditor/static/mdeditor/images/logos/editormd-favicon-64x64.ico
flask_mdeditor/static/mdeditor/images/logos/editormd-logo-114x114.png
flask_mdeditor/static/mdeditor/images/logos/editormd-logo-120x120.png
flask_mdeditor/static/mdeditor/images/logos/editormd-logo-144x144.png
flask_mdeditor/static/mdeditor/images/logos/editormd-logo-16x16.png
flask_mdeditor/static/mdeditor/images/logos/editormd-logo-180x180.png
flask_mdeditor/static/mdeditor/images/logos/editormd-logo-240x240.png
